CHANGES.txt
DEPENDENCES.txt
README.txt
setup.py
src/ng/__init__.py
src/ng.content.remotearticle.egg-info/PKG-INFO
src/ng.content.remotearticle.egg-info/SOURCES.txt
src/ng.content.remotearticle.egg-info/dependency_links.txt
src/ng.content.remotearticle.egg-info/namespace_packages.txt
src/ng.content.remotearticle.egg-info/not-zip-safe
src/ng.content.remotearticle.egg-info/requires.txt
src/ng.content.remotearticle.egg-info/top_level.txt
src/ng/content/__init__.py
src/ng/content/remotearticle/__init__.py
src/ng/content/remotearticle/configure.zcml
src/ng/content/remotearticle/ng.content.remotearticle.txt
src/ng/content/remotearticle/remotearticle/__init__.py
src/ng/content/remotearticle/remotearticle/configure.zcml
src/ng/content/remotearticle/remotearticle/interfaces.py
src/ng/content/remotearticle/remotearticle/remotearticle.py
src/ng/content/remotearticle/remotearticle/remotearticle.txt
src/ng/content/remotearticle/remotearticle/browser/__init__.py
src/ng/content/remotearticle/remotearticle/browser/configure.zcml
src/ng/content/remotearticle/remotearticle/browser/editform.py
src/ng/content/remotearticle/remotedivision/interfaces.py
